NiukeShejiGangQiuzhiJingyanFenxiang20212022Fix1/README.md
NiukeShejiGangQiuzhiJingyanFenxiang20212022Fix1/__init__.py
NiukeShejiGangQiuzhiJingyanFenxiang20212022Fix1/__main__.py
NiukeShejiGangQiuzhiJingyanFenxiang20212022Fix1/file.epub
NiukeShejiGangQiuzhiJingyanFenxiang20212022Fix1/index.html
NiukeShejiGangQiuzhiJingyanFenxiang20212022Fix1/css/__init__.py
NiukeShejiGangQiuzhiJingyanFenxiang20212022Fix1/css/annotations.css
NiukeShejiGangQiuzhiJingyanFenxiang20212022Fix1/css/main.css
NiukeShejiGangQiuzhiJingyanFenxiang20212022Fix1/css/normalize.css
NiukeShejiGangQiuzhiJingyanFenxiang20212022Fix1/css/popup.css
NiukeShejiGangQiuzhiJingyanFenxiang20212022Fix1/font/__init__.py
NiukeShejiGangQiuzhiJingyanFenxiang20212022Fix1/font/fontello.eot
NiukeShejiGangQiuzhiJingyanFenxiang20212022Fix1/font/fontello.svg
NiukeShejiGangQiuzhiJingyanFenxiang20212022Fix1/font/fontello.ttf
NiukeShejiGangQiuzhiJingyanFenxiang20212022Fix1/font/fontello.woff
NiukeShejiGangQiuzhiJingyanFenxiang20212022Fix1/img/__init__.py
NiukeShejiGangQiuzhiJingyanFenxiang20212022Fix1/img/annotator-glyph-sprite.png
NiukeShejiGangQiuzhiJingyanFenxiang20212022Fix1/img/annotator-icon-sprite.png
NiukeShejiGangQiuzhiJingyanFenxiang20212022Fix1/img/apple-touch-icon.png
NiukeShejiGangQiuzhiJingyanFenxiang20212022Fix1/img/cancelfullscreen.png
NiukeShejiGangQiuzhiJingyanFenxiang20212022Fix1/img/close.png
NiukeShejiGangQiuzhiJingyanFenxiang20212022Fix1/img/fullscreen.png
NiukeShejiGangQiuzhiJingyanFenxiang20212022Fix1/img/loader.gif
NiukeShejiGangQiuzhiJingyanFenxiang20212022Fix1/img/menu-icon.png
NiukeShejiGangQiuzhiJingyanFenxiang20212022Fix1/img/save.png
NiukeShejiGangQiuzhiJingyanFenxiang20212022Fix1/img/saved.png
NiukeShejiGangQiuzhiJingyanFenxiang20212022Fix1/img/settings-s.png
NiukeShejiGangQiuzhiJingyanFenxiang20212022Fix1/img/settings.png
NiukeShejiGangQiuzhiJingyanFenxiang20212022Fix1/img/star.png
NiukeShejiGangQiuzhiJingyanFenxiang20212022Fix1/js/__init__.py
niuke_sheji_gang_qiuzhi_jingyan_fenxiang_2021_2022_fix1-2025.3.25.1.dist-info/METADATA
niuke_sheji_gang_qiuzhi_jingyan_fenxiang_2021_2022_fix1-2025.3.25.1.dist-info/WHEEL
niuke_sheji_gang_qiuzhi_jingyan_fenxiang_2021_2022_fix1-2025.3.25.1.dist-info/entry_points.txt
niuke_sheji_gang_qiuzhi_jingyan_fenxiang_2021_2022_fix1-2025.3.25.1.dist-info/top_level.txt
niuke_sheji_gang_qiuzhi_jingyan_fenxiang_2021_2022_fix1-2025.3.25.1.dist-info/RECORD
